collectionfield/__init__.py
collectionfield/converter.py
collectionfield/forms.py
collectionfield/validators.py
collectionfield/models/__init__.py
collectionfield/models/fields.py
collectionfield/models/lookups.py
collectionfield/tests/__init__.py
collectionfield/tests/forms.py
collectionfield/tests/models.py
collectionfield/tests/tests.py
django3_collectionfield-1.0.0.dist-info/LICENSE
django3_collectionfield-1.0.0.dist-info/METADATA
django3_collectionfield-1.0.0.dist-info/WHEEL
django3_collectionfield-1.0.0.dist-info/top_level.txt
django3_collectionfield-1.0.0.dist-info/RECORD
