Metadata-Version: 1.1
Name: django3-collectionfield
Version: 1.0.0
Summary: Custom Django model field to store multiple values.
Home-page: https://github.com/metalbass/django3-collectionfield
Author: Pawel Scierski
Author-email: escer@protonmail.com
License: MIT
Keywords: django models fields collections
Platform: UNKNOWN
Classifier: Development Status :: 3 - Alpha
Classifier: Intended Audience :: Developers
Classifier: Environment :: Web Environment
Classifier: License :: OSI Approved :: MIT License
Classifier: Operating System :: OS Independent
Classifier: Programming Language :: Python :: 3
Classifier: Programming Language :: Python :: 3.4
Classifier: Programming Language :: Python :: 3.5
Classifier: Framework :: Django :: 3.0
Classifier: Topic :: Internet :: WWW/HTTP
